devtools_aspect_ratio/__init__.py
devtools_aspect_ratio-1.0.1.dist-info/METADATA
devtools_aspect_ratio-1.0.1.dist-info/WHEEL
devtools_aspect_ratio-1.0.1.dist-info/top_level.txt
devtools_aspect_ratio-1.0.1.dist-info/RECORD
