Metadata-Version: 2.1
Name: devtools-aspect-ratio
Version: 1.0.1
Summary: Aspect ratio calculator
Home-page: https://devtools.at/tools/aspect-ratio-calculator
Author: DevTools.at
Author-email: hello@devtools.at
Project-URL: Homepage, https://devtools.at/tools/aspect-ratio-calculator
Project-URL: Repository, https://github.com/devtools-at/aspect-ratio-calculator
Classifier: Development Status :: 4 - Beta
Classifier: Intended Audience :: Developers
Classifier: License :: OSI Approved :: MIT License
Classifier: Programming Language :: Python :: 3
Requires-Python: >=3.8
